barrelshifter_code.v
module barrel_shifter_32bit (
    input  wire [31:0] data_in,   // 32-bit Input Data
    input  wire [4:0]  shift_amt, // 5-bit Shift Amount (0 to 31)
    input  wire [1:0]  shift_type,// 00: LSL, 01: LSR, 10: ASR, 11: ROR
    output reg  [31:0] data_out   // 32-bit Shifted Output Data
);

    reg [31:0] stage0, stage1, stage2, stage3;
    wire fill_bit;

    // Determine the sign-extension bit for Arithmetic Right Shift (ASR)
    assign fill_bit = (shift_type == 2'b10) ? data_in[31] : 1'b0;

    always @(*) begin
        // STAGE 0: Shift/Rotate by 1 bit (Controlled by shift_amt[0])
        if (shift_amt[0]) begin
            case (shift_type)
                2'b00:   stage0 = {data_in[30:0], 1'b0};               // Logical Left Shift
                2'b01:   stage0 = {1'b0, data_in[31:1]};               // Logical Right Shift
                2'b10:   stage0 = {fill_bit, data_in[31:1]};           // Arithmetic Right Shift
                2'b11:   stage0 = {data_in[0], data_in[31:1]};         // Rotate Right
                default: stage0 = data_in;
            endcase
        end else begin
            stage0 = data_in;
        end

        // STAGE 1: Shift/Rotate by 2 bits (Controlled by shift_amt[1])
        if (shift_amt[1]) begin
            case (shift_type)
                2'b00:   stage1 = {stage0[29:0], 2'b0};
                2'b01:   stage1 = {2'b0, stage0[31:2]};
                2'b10:   stage1 = {{2{fill_bit}}, stage0[31:2]};
                2'b11:   stage1 = {stage0[1:0], stage0[31:2]};
                default: stage1 = stage0;
            endcase
        end else begin
            stage1 = stage0;
        end

        // STAGE 2: Shift/Rotate by 4 bits (Controlled by shift_amt[2])
        if (shift_amt[2]) begin
            case (shift_type)
                2'b00:   stage2 = {stage1[27:0], 4'b0};
                2'b01:   stage2 = {4'b0, stage1[31:4]};
                2'b10:   stage2 = {{4{fill_bit}}, stage1[31:4]};
                2'b11:   stage2 = {stage1[3:0], stage1[31:4]};
                default: stage2 = stage1;
            endcase
        end else begin
            stage2 = stage1;
        end

        // STAGE 3: Shift/Rotate by 8 bits (Controlled by shift_amt[3])
        if (shift_amt[3]) begin
            case (shift_type)
                2'b00:   stage3 = {stage2[23:0], 8'b0};
                2'b01:   stage3 = {8'b0, stage2[31:8]};
                2'b10:   stage3 = {{8{fill_bit}}, stage2[31:8]};
                2'b11:   stage3 = {stage2[7:0], stage2[31:8]};
                default: stage3 = stage2;
            endcase
        end else begin
            stage3 = stage2;
        end

        // STAGE 4: Shift/Rotate by 16 bits (Controlled by shift_amt[4])
        if (shift_amt[4]) begin
            case (shift_type)
                2'b00:   data_out = {stage3[15:0], 16'b0};
                2'b01:   data_out = {16'b0, stage3[31:16]};
                2'b10:   data_out = {{16{fill_bit}}, stage3[31:16]};
                2'b11:   data_out = {stage3[15:0], stage3[31:16]};
                default: data_out = stage3;
            endcase
        end else begin
            data_out = stage3;
        end
    end
endmodule

3.boothmultiplier.v
module bmul(
    input clk,
    input rst,
    input start,
    input [31:0] multiplier,
    input [31:0] multiplicand,
    output reg [63:0] ans,
    output reg done
);
    reg [31:0] m_comp;
    reg q;
    reg [5:0] count;

    always @(posedge clk or posedge rst) begin
        if(rst) begin
            ans   <= 64'b0;
            m_comp<= 32'b0;
            q     <= 1'b0;
            count <= 6'd0;
            done  <= 1'b0;
        end
        else if(start) begin
            ans   <= {32'b0, multiplier};
            m_comp<= ~multiplicand + 1'b1;
            q     <= 1'b0;
            count <= 6'd32;
            done  <= 1'b0;
        end
        else if(count > 0) begin
            case ({ans[0], q})        
                2'b01: begin 
                    {ans, q} <= $signed({ans[63:32] + multiplicand, ans[31:0], q}) >>> 1;
                end
                2'b10: begin 
                    {ans, q} <= $signed({ans[63:32] + m_comp, ans[31:0], q}) >>> 1;
                end
                default: begin 
                    {ans, q} <= $signed({ans, q}) >>> 1;
                end
            endcase

            count <= count - 1'b1;
            if (count == 6'd1) begin
                done <= 1'b1;
            end
        end
    end
endmodule

alu_main_code.v
module alu_32_bit(
    output reg signed [31:0] alu_out,
    output reg [32:0]        temp,
    output reg               zero,
    output reg               carry,
    output reg               overflow,
    output reg               difference,
    output wire [63:0]       mul_ans,    
    output wire              mul_done,   
    input signed [31:0]      in_a,
    input signed [31:0]      in_b,
    input [2:0]              op,
    input                    clk,
    input                    rst,        
    input                    mul_start 
);

  // Internal routing wires to intercept module outputs
  wire [63:0] booth_out;
  wire [31:0] barrel_out;
   
  assign mul_ans = booth_out;

  // Instantiation of Booth Multiplier module
  bmul booth_inst (
      .clk(clk),
      .rst(rst),
      .start(mul_start),
      .multiplier(in_a),
      .multiplicand(in_b),
      .ans(booth_out),
      .done(mul_done)
  );

  // Instantiation of your verified Logarithmic Barrel Shifter module
  // in_b[6:2] extracts the 5-bit shift amount (0 to 31)
  // in_b[1:0] extracts the 2-bit shift type (LSL, LSR, ASR, ROR)
  barrel_shifter_32bit barrel_inst (
      .data_in(in_a),
      .shift_amt(in_b[6:2]),
      .shift_type(in_b[1:0]),
      .data_out(barrel_out)
  );

  // =========================================================================
  // 2. BUS ROUTING AND ALU OPERATION SELECT
  // =========================================================================
  always @(*) begin
    // Reset defaults to prevent hardware latches
    temp       = 33'b0;
    carry      = 1'b0;
    difference = 1'b0;
    overflow   = 1'b0;
    
    case(op)
      3'b000: alu_out = 32'b0;
      
      // Addition
      3'b001: begin
        temp    = in_a + in_b;
        alu_out = temp[31:0];
        carry   = temp[32];
        overflow = (in_a[31] == in_b[31]) && (alu_out[31] != in_a[31]);
      end
      
      // Subtraction
      3'b010: begin
        temp    = in_a - in_b;
        alu_out = temp[31:0];
        difference = temp[32];
        overflow = (in_a[31] != in_b[31]) && (alu_out[31] != in_a[31]);
      end
      
      // Booth Multiplier Sub-Module Connection
      3'b011: alu_out = booth_out[31:0]; 
      
      // Bitwise OR (FIX: Corrected literal width prefix from 4'b100 to 3'b100)
      3'b100: alu_out = in_a | in_b;   
      
      // Barrel Shifter Sub-Module Connection (Replaces old XOR)
      3'b101: alu_out = barrel_out;    
      
      // Fixed 1-bit shifts
      3'b110: alu_out = in_a&in_b;     // Logical AND
      3'b111: alu_out = in_a^in_b;     // Logical XOR
      default: alu_out = 32'b1;         
    endcase
    
    // Status flag generation
    zero = (alu_out == 32'b0);
  end
endmodule

alu_testcode.v
module alu_32_bit_tb;

    // Inputs to the ALU Subsystem (Declared as registers)
    reg signed [31:0] in_a;
    reg signed [31:0] in_b;
    reg        [2:0]  op;
    reg               clk;
    reg               rst;
    reg               mul_start;

    // Outputs from the ALU Subsystem (Declared as wires)
    wire        [31:0] alu_out;
    wire        [32:0] temp;
    wire               zero;
    wire               carry;
    wire               overflow;
    wire               difference;
    wire        [63:0] mul_ans;
    wire               mul_done;

    // Sign-extended monitoring wire for print readability
    wire signed [31:0] alu_out_signed;
    assign alu_out_signed = alu_out;

    // Instantiate the Unified Top-Level ALU Module
    alu_32_bit uut (
        .alu_out(alu_out),
        .temp(temp),
        .zero(zero),
        .carry(carry),
        .overflow(overflow),
        .difference(difference),
        .mul_ans(mul_ans),
        .mul_done(mul_done),
        .in_a(in_a),
        .in_b(in_b),
        .op(op),
        .clk(clk),
        .rst(rst),
        .mul_start(mul_start)
    );

    // Clock Generation: 10ns cycle period (50MHz simulation environment)
    initial begin
        clk = 0;
        forever #5 clk = ~clk;
    end

    // Main Test Vector Sequence
    initial begin
        // Setup Waveform Dumps for VS Code / GTKWave inspection
        $dumpfile("alu_system_wave.vcd");
        $dumpvars(0, alu_32_bit_tb);

        $display("=============================================================");
        $display("  STARTING INTEGRATED SYSTEM VERIFICATION (ALU + BMUL + BARREL)");
        $display("=============================================================");

        // PHASE 1: System Hardware Initialization & Reset
        rst       = 1'b1;
        mul_start = 1'b0;
        op        = 3'b000;
        in_a      = 32'b0;
        in_b      = 32'b0;
        #15; 
        rst       = 1'b0; // Release hardware reset
        #5;

        // PHASE 2: Core Arithmetic Tests (Addition & Subtraction)
        // Case 2A: Addition (15 + 10 = 25)
        in_a = 32'd15; 
        in_b = 32'd10; 
        op   = 3'b001; 
        #10;
        $display("[ADD] InA=%0d, InB=%0d | Out=%0d (Expected: 25)", in_a, in_b, alu_out_signed);

        // Case 2B: Subtraction (15 - 10 = 5)
        op   = 3'b010; 
        #10;
        $display("[SUB] InA=%0d, InB=%0d | Out=%0d (Expected: 5)", in_a, in_b, alu_out_signed);

        // -----------------------------------------------------------------
        // PHASE 3: Booth Multiplier Test (Opcode 3'b011)
        // -----------------------------------------------------------------
        // Test: 50 * -10 = -500
        in_a = 32'd50;   // Multiplier
        in_b = -32'd10;  // Multiplicand
        op   = 3'b011;   // Steer ALU out bus to track multiplier output
        #10;
        
        // Pulse the start trigger for exactly one clock cycle
        mul_start = 1'b1; #10;
        mul_start = 1'b0;

        // Block execution and wait until the sequential engine asserts done flag (32 cycles)
        @(posedge mul_done);
        #5; // Structural settling delay
        $display("[BOOTH MUL] InA=%0d, InB=%0d | Full 64-bit Ans=%0d | ALU Bus Out=%0d", 
                 in_a, in_b, $signed(mul_ans), alu_out_signed);

        // PHASE 4: Logarithmic Barrel Shifter Tests (Opcode 3'b101)
        op   = 3'b101;
        in_a = 32'h0000_000F; // Test pattern data

        // Case 4A: Logical Shift Left (LSL) by 4 bits
        // in_b structure: {25'b0, shift_amt(5'd4), shift_type(2'b00)} -> 00100_00 -> 32'h0000_0010
        in_b = 32'h0000_0010; 
        #10;
        $display("[BARREL LSL] InA=%h, Amt=4 | Out=%h (Expected: 000000f0)", in_a, alu_out);

        // Case 4B: Logical Shift Right (LSR) by 2 bits
        // in_b structure: {25'b0, shift_amt(5'd2), shift_type(2'b01)} -> 00010_01 -> 32'h0000_0009
        in_a = 32'hF000_0000;
        in_b = 32'h0000_0009; 
        #10;
        $display("[BARREL LSR] InA=%h, Amt=2 | Out=%h (Expected: 3c000000)", in_a, alu_out);

        // Case 4C: Rotate Right (ROR) by 4 bits
        // in_b structure: {25'b0, shift_amt(5'd4), shift_type(2'b11)} -> 00100_11 -> 32'h0000_0013
        in_a = 32'h1234_5678;
        in_b = 32'h0000_0013; 
        #10;
        $display("[BARREL ROR] InA=%h, Amt=4 | Out=%h (Expected: 81234567)", in_a, alu_out);

        // -----------------------------------------------------------------
        // PHASE 5: Bitwise Operations(AND,OR,XOR)
        // -----------------------------------------------------------------
        in_a = 32'h5A5A_5A5A;
        in_b = 32'h0F0F_0F0F;
        
        op   = 3'b100; #10; // Bitwise OR
        $display("[BITWISE OR] InA=%h, InB=%h | Out=%h", in_a, in_b, alu_out);

        in_a = 32'h5A5A_5A5A;
        in_b = 32'h0F0F_0F0F;
        op   = 3'b110; #10; // Bitwise AND
        $display("[BITWISE AND] InA=%h, InB=%h | Out=%h", in_a, in_b, alu_out);


        op   = 3'b111; #10; // Bitwise XOR
        $display("[BITWISE XOR] InA=%h, InB=%h | Out=%h", in_a, in_b, alu_out);

        // -----------------------------------------------------------------
        // Final Execution Wrap-up
        // -----------------------------------------------------------------
        $display("=============================================================");
        $display("  VERIFICATION COMPLETE SUCCESSFULLY");
        $display("=============================================================");
        $finish;
    end

endmodule

alu_system_wave.vcd
$date
	Wed Sep 30 13:29:11 2026
$end
$version
	Icarus Verilog
$end
$timescale
	1s
$end
$scope module alu_32_bit_tb $end
$var wire 32 ! alu_out_signed [31:0] $end
$var wire 1 " zero $end
$var wire 33 # temp [32:0] $end
$var wire 1 $ overflow $end
$var wire 1 % mul_done $end
$var wire 64 & mul_ans [63:0] $end
$var wire 1 ' difference $end
$var wire 1 ( carry $end
$var wire 32 ) alu_out [31:0] $end
$var reg 1 * clk $end
$var reg 32 + in_a [31:0] $end
$var reg 32 , in_b [31:0] $end
$var reg 1 - mul_start $end
$var reg 3 . op [2:0] $end
$var reg 1 / rst $end
$scope module uut $end
$var wire 1 * clk $end
$var wire 32 0 in_a [31:0] $end
$var wire 32 1 in_b [31:0] $end
$var wire 64 2 mul_ans [63:0] $end
$var wire 1 - mul_start $end
$var wire 3 3 op [2:0] $end
$var wire 1 / rst $end
$var wire 1 % mul_done $end
$var wire 64 4 booth_out [63:0] $end
$var wire 32 5 barrel_out [31:0] $end
$var reg 32 6 alu_out [31:0] $end
$var reg 1 ( carry $end
$var reg 1 ' difference $end
$var reg 1 $ overflow $end
$var reg 33 7 temp [32:0] $end
$var reg 1 " zero $end
$scope module barrel_inst $end
$var wire 32 8 data_in [31:0] $end
$var wire 5 9 shift_amt [4:0] $end
$var wire 2 : shift_type [1:0] $end
$var wire 1 ; fill_bit $end
$var reg 32 < data_out [31:0] $end
$var reg 32 = stage0 [31:0] $end
$var reg 32 > stage1 [31:0] $end
$var reg 32 ? stage2 [31:0] $end
$var reg 32 @ stage3 [31:0] $end
$upscope $end
$scope module booth_inst $end
$var wire 1 * clk $end
$var wire 32 A multiplicand [31:0] $end
$var wire 32 B multiplier [31:0] $end
$var wire 1 / rst $end
$var wire 1 - start $end
$var reg 64 C ans [63:0] $end
$var reg 6 D count [5:0] $end
$var reg 1 % done $end
$var reg 32 E m_comp [31:0] $end
$var reg 1 F q $end
$upscope $end
$upscope $end
$upscope $end
$enddefinitions $end
$comment Show the parameter values. $end
$dumpall
$end
#0
$dumpvars
0F
b0 E
b0 D
b0 C
b0 B
b0 A
b0 @
b0 ?
b0 >
b0 =
b0 <
0;
b0 :
b0 9
b0 8
b0 7
b0 6
b0 5
b0 4
b0 3
b0 2
b0 1
b0 0
1/
b0 .
0-
b0 ,
b0 +
0*
b0 )
0(
0'
b0 &
0%
0$
b0 #
1"
b0 !
$end
#5
1*
#10
0*
#15
1*
0/
#20
b10 9
b10 :
b11 5
b11 <
b11 @
b11 ?
b11 >
b1111 =
0"
b11001 !
b11001 )
b11001 6
b11001 #
b11001 7
0*
b1 .
b1 3
b1010 ,
b1010 1
b1010 A
b1111 +
b1111 0
b1111 8
b1111 B
#25
1*
#30
b101 !
b101 )
b101 6
b101 #
b101 7
0*
b10 .
b10 3
#35
1*
#40
b11101 9
b0 5
b0 <
b0 @
b1 ?
b11001 >
b11001 =
1"
b0 !
b0 )
b0 6
b0 #
b0 7
0*
b11 .
b11 3
b11111111111111111111111111110110 ,
b11111111111111111111111111110110 1
b11111111111111111111111111110110 A
b110010 +
b110010 0
b110010 8
b110010 B
#45
1*
#50
0*
1-
#55
0"
b110010 !
b110010 )
b110010 6
b100000 D
b1010 E
b110010 &
b110010 2
b110010 4
b110010 C
1*
#60
0*
0-
#65
b11001 !
b11001 )
b11001 6
b11111 D
b11001 &
b11001 2
b11001 4
b11001 C
1*
#70
0*
#75
b1100 !
b1100 )
b1100 6
b11110 D
b10100000000000000000000000000001100 &
b10100000000000000000000000000001100 2
b10100000000000000000000000000001100 4
b10100000000000000000000000000001100 C
1F
1*
#80
0*
#85
b10000000000000000000000000000110 !
b10000000000000000000000000000110 )
b10000000000000000000000000000110 6
b11101 D
b1111111111111111111111111111110110000000000000000000000000000110 &
b1111111111111111111111111111110110000000000000000000000000000110 2
b1111111111111111111111111111110110000000000000000000000000000110 4
b1111111111111111111111111111110110000000000000000000000000000110 C
0F
1*
#90
0*
#95
b11000000000000000000000000000011 !
b11000000000000000000000000000011 )
b11000000000000000000000000000011 6
b11100 D
b1111111111111111111111111111111011000000000000000000000000000011 &
b1111111111111111111111111111111011000000000000000000000000000011 2
b1111111111111111111111111111111011000000000000000000000000000011 4
b1111111111111111111111111111111011000000000000000000000000000011 C
1*
#100
0*
#105
b1100000000000000000000000000001 !
b1100000000000000000000000000001 )
b1100000000000000000000000000001 6
b11011 D
b10001100000000000000000000000000001 &
b10001100000000000000000000000000001 2
b10001100000000000000000000000000001 4
b10001100000000000000000000000000001 C
1F
1*
#110
0*
#115
b110000000000000000000000000000 !
b110000000000000000000000000000 )
b110000000000000000000000000000 6
b11010 D
b1000110000000000000000000000000000 &
b1000110000000000000000000000000000 2
b1000110000000000000000000000000000 4
b1000110000000000000000000000000000 C
1*
#120
0*
#125
b11000000000000000000000000000 !
b11000000000000000000000000000 )
b11000000000000000000000000000 6
b11001 D
b1111111111111111111111111111110000011000000000000000000000000000 &
b1111111111111111111111111111110000011000000000000000000000000000 2
b1111111111111111111111111111110000011000000000000000000000000000 4
b1111111111111111111111111111110000011000000000000000000000000000 C
0F
1*
#130
0*
#135
b1100000000000000000000000000 !
b1100000000000000000000000000 )
b1100000000000000000000000000 6
b11000 D
b1111111111111111111111111111111000001100000000000000000000000000 &
b1111111111111111111111111111111000001100000000000000000000000000 2
b1111111111111111111111111111111000001100000000000000000000000000 4
b1111111111111111111111111111111000001100000000000000000000000000 C
1*
#140
0*
#145
b110000000000000000000000000 !
b110000000000000000000000000 )
b110000000000000000000000000 6
b10111 D
b1111111111111111111111111111111100000110000000000000000000000000 &
b1111111111111111111111111111111100000110000000000000000000000000 2
b1111111111111111111111111111111100000110000000000000000000000000 4
b1111111111111111111111111111111100000110000000000000000000000000 C
1*
#150
0*
#155
b10000011000000000000000000000000 !
b10000011000000000000000000000000 )
b10000011000000000000000000000000 6
b10110 D
b1111111111111111111111111111111110000011000000000000000000000000 &
b1111111111111111111111111111111110000011000000000000000000000000 2
b1111111111111111111111111111111110000011000000000000000000000000 4
b1111111111111111111111111111111110000011000000000000000000000000 C
1*
#160
0*
#165
b11000001100000000000000000000000 !
b11000001100000000000000000000000 )
b11000001100000000000000000000000 6
b10101 D
b1111111111111111111111111111111111000001100000000000000000000000 &
b1111111111111111111111111111111111000001100000000000000000000000 2
b1111111111111111111111111111111111000001100000000000000000000000 4
b1111111111111111111111111111111111000001100000000000000000000000 C
1*
#170
0*
#175
b11100000110000000000000000000000 !
b11100000110000000000000000000000 )
b11100000110000000000000000000000 6
b10100 D
b1111111111111111111111111111111111100000110000000000000000000000 &
b1111111111111111111111111111111111100000110000000000000000000000 2
b1111111111111111111111111111111111100000110000000000000000000000 4
b1111111111111111111111111111111111100000110000000000000000000000 C
1*
#180
0*
#185
b11110000011000000000000000000000 !
b11110000011000000000000000000000 )
b11110000011000000000000000000000 6
b10011 D
b1111111111111111111111111111111111110000011000000000000000000000 &
b1111111111111111111111111111111111110000011000000000000000000000 2
b1111111111111111111111111111111111110000011000000000000000000000 4
b1111111111111111111111111111111111110000011000000000000000000000 C
1*
#190
0*
#195
b11111000001100000000000000000000 !
b11111000001100000000000000000000 )
b11111000001100000000000000000000 6
b10010 D
b1111111111111111111111111111111111111000001100000000000000000000 &
b1111111111111111111111111111111111111000001100000000000000000000 2
b1111111111111111111111111111111111111000001100000000000000000000 4
b1111111111111111111111111111111111111000001100000000000000000000 C
1*
#200
0*
#205
b11111100000110000000000000000000 !
b11111100000110000000000000000000 )
b11111100000110000000000000000000 6
b10001 D
b1111111111111111111111111111111111111100000110000000000000000000 &
b1111111111111111111111111111111111111100000110000000000000000000 2
b1111111111111111111111111111111111111100000110000000000000000000 4
b1111111111111111111111111111111111111100000110000000000000000000 C
1*
#210
0*
#215
b11111110000011000000000000000000 !
b11111110000011000000000000000000 )
b11111110000011000000000000000000 6
b10000 D
b1111111111111111111111111111111111111110000011000000000000000000 &
b1111111111111111111111111111111111111110000011000000000000000000 2
b1111111111111111111111111111111111111110000011000000000000000000 4
b1111111111111111111111111111111111111110000011000000000000000000 C
1*
#220
0*
#225
b11111111000001100000000000000000 !
b11111111000001100000000000000000 )
b11111111000001100000000000000000 6
b1111 D
b1111111111111111111111111111111111111111000001100000000000000000 &
b1111111111111111111111111111111111111111000001100000000000000000 2
b1111111111111111111111111111111111111111000001100000000000000000 4
b1111111111111111111111111111111111111111000001100000000000000000 C
1*
#230
0*
#235
b11111111100000110000000000000000 !
b11111111100000110000000000000000 )
b11111111100000110000000000000000 6
b1110 D
b1111111111111111111111111111111111111111100000110000000000000000 &
b1111111111111111111111111111111111111111100000110000000000000000 2
b1111111111111111111111111111111111111111100000110000000000000000 4
b1111111111111111111111111111111111111111100000110000000000000000 C
1*
#240
0*
#245
b11111111110000011000000000000000 !
b11111111110000011000000000000000 )
b11111111110000011000000000000000 6
b1101 D
b1111111111111111111111111111111111111111110000011000000000000000 &
b1111111111111111111111111111111111111111110000011000000000000000 2
b1111111111111111111111111111111111111111110000011000000000000000 4
b1111111111111111111111111111111111111111110000011000000000000000 C
1*
#250
0*
#255
b11111111111000001100000000000000 !
b11111111111000001100000000000000 )
b11111111111000001100000000000000 6
b1100 D
b1111111111111111111111111111111111111111111000001100000000000000 &
b1111111111111111111111111111111111111111111000001100000000000000 2
b1111111111111111111111111111111111111111111000001100000000000000 4
b1111111111111111111111111111111111111111111000001100000000000000 C
1*
#260
0*
#265
b11111111111100000110000000000000 !
b11111111111100000110000000000000 )
b11111111111100000110000000000000 6
b1011 D
b1111111111111111111111111111111111111111111100000110000000000000 &
b1111111111111111111111111111111111111111111100000110000000000000 2
b1111111111111111111111111111111111111111111100000110000000000000 4
b1111111111111111111111111111111111111111111100000110000000000000 C
1*
#270
0*
#275
b11111111111110000011000000000000 !
b11111111111110000011000000000000 )
b11111111111110000011000000000000 6
b1010 D
b1111111111111111111111111111111111111111111110000011000000000000 &
b1111111111111111111111111111111111111111111110000011000000000000 2
b1111111111111111111111111111111111111111111110000011000000000000 4
b1111111111111111111111111111111111111111111110000011000000000000 C
1*
#280
0*
#285
b11111111111111000001100000000000 !
b11111111111111000001100000000000 )
b11111111111111000001100000000000 6
b1001 D
b1111111111111111111111111111111111111111111111000001100000000000 &
b1111111111111111111111111111111111111111111111000001100000000000 2
b1111111111111111111111111111111111111111111111000001100000000000 4
b1111111111111111111111111111111111111111111111000001100000000000 C
1*
#290
0*
#295
b11111111111111100000110000000000 !
b11111111111111100000110000000000 )
b11111111111111100000110000000000 6
b1000 D
b1111111111111111111111111111111111111111111111100000110000000000 &
b1111111111111111111111111111111111111111111111100000110000000000 2
b1111111111111111111111111111111111111111111111100000110000000000 4
b1111111111111111111111111111111111111111111111100000110000000000 C
1*
#300
0*
#305
b11111111111111110000011000000000 !
b11111111111111110000011000000000 )
b11111111111111110000011000000000 6
b111 D
b1111111111111111111111111111111111111111111111110000011000000000 &
b1111111111111111111111111111111111111111111111110000011000000000 2
b1111111111111111111111111111111111111111111111110000011000000000 4
b1111111111111111111111111111111111111111111111110000011000000000 C
1*
#310
0*
#315
b11111111111111111000001100000000 !
b11111111111111111000001100000000 )
b11111111111111111000001100000000 6
b110 D
b1111111111111111111111111111111111111111111111111000001100000000 &
b1111111111111111111111111111111111111111111111111000001100000000 2
b1111111111111111111111111111111111111111111111111000001100000000 4
b1111111111111111111111111111111111111111111111111000001100000000 C
1*
#320
0*
#325
b11111111111111111100000110000000 !
b11111111111111111100000110000000 )
b11111111111111111100000110000000 6
b101 D
b1111111111111111111111111111111111111111111111111100000110000000 &
b1111111111111111111111111111111111111111111111111100000110000000 2
b1111111111111111111111111111111111111111111111111100000110000000 4
b1111111111111111111111111111111111111111111111111100000110000000 C
1*
#330
0*
#335
b11111111111111111110000011000000 !
b11111111111111111110000011000000 )
b11111111111111111110000011000000 6
b100 D
b1111111111111111111111111111111111111111111111111110000011000000 &
b1111111111111111111111111111111111111111111111111110000011000000 2
b1111111111111111111111111111111111111111111111111110000011000000 4
b1111111111111111111111111111111111111111111111111110000011000000 C
1*
#340
0*
#345
b11111111111111111111000001100000 !
b11111111111111111111000001100000 )
b11111111111111111111000001100000 6
b11 D
b1111111111111111111111111111111111111111111111111111000001100000 &
b1111111111111111111111111111111111111111111111111111000001100000 2
b1111111111111111111111111111111111111111111111111111000001100000 4
b1111111111111111111111111111111111111111111111111111000001100000 C
1*
#350
0*
#355
b11111111111111111111100000110000 !
b11111111111111111111100000110000 )
b11111111111111111111100000110000 6
b10 D
b1111111111111111111111111111111111111111111111111111100000110000 &
b1111111111111111111111111111111111111111111111111111100000110000 2
b1111111111111111111111111111111111111111111111111111100000110000 4
b1111111111111111111111111111111111111111111111111111100000110000 C
1*
#360
0*
#365
b11111111111111111111110000011000 !
b11111111111111111111110000011000 )
b11111111111111111111110000011000 6
b1 D
b1111111111111111111111111111111111111111111111111111110000011000 &
b1111111111111111111111111111111111111111111111111111110000011000 2
b1111111111111111111111111111111111111111111111111111110000011000 4
b1111111111111111111111111111111111111111111111111111110000011000 C
1*
#370
0*
#375
b11111111111111111111111000001100 !
b11111111111111111111111000001100 )
b11111111111111111111111000001100 6
1%
b0 D
b1111111111111111111111111111111111111111111111111111111000001100 &
b1111111111111111111111111111111111111111111111111111111000001100 2
b1111111111111111111111111111111111111111111111111111111000001100 4
b1111111111111111111111111111111111111111111111111111111000001100 C
1*
#380
b11110000 5
b11110000 <
b11110000 @
b100 9
b0 :
b11110000 ?
b1111 >
b1111 =
0"
b11110000 !
b11110000 )
b11110000 6
b10000 ,
b10000 1
b10000 A
b1111 +
b1111 0
b1111 8
b1111 B
b101 .
b101 3
0*
#385
1*
#390
0"
b111100000000000000000000000000 !
b111100000000000000000000000000 )
b111100000000000000000000000000 6
b10 9
b1 :
b111100000000000000000000000000 5
b111100000000000000000000000000 <
b111100000000000000000000000000 @
b111100000000000000000000000000 ?
b111100000000000000000000000000 >
b11110000000000000000000000000000 =
0*
b1001 ,
b1001 1
b1001 A
b11110000000000000000000000000000 +
b11110000000000000000000000000000 0
b11110000000000000000000000000000 8
b11110000000000000000000000000000 B
#395
1*
#400
b10000001001000110100010101100111 !
b10000001001000110100010101100111 )
b10000001001000110100010101100111 6
b100 9
b11 :
b10000001001000110100010101100111 5
b10000001001000110100010101100111 <
b10000001001000110100010101100111 @
b10000001001000110100010101100111 ?
b10010001101000101011001111000 >
b10010001101000101011001111000 =
0*
b10011 ,
b10011 1
b10011 A
b10010001101000101011001111000 +
b10010001101000101011001111000 0
b10010001101000101011001111000 8
b10010001101000101011001111000 B
#405
1*
#410
b11 9
b1001011010010110100101101001011 5
b1001011010010110100101101001011 <
b1001011010010110100101101001011 @
b1001011010010110100101101001011 ?
b1001011010010110100101101001011 >
b101101001011010010110100101101 =
b1011111010111110101111101011111 !
b1011111010111110101111101011111 )
b1011111010111110101111101011111 6
0*
b100 .
b100 3
b1111000011110000111100001111 ,
b1111000011110000111100001111 1
b1111000011110000111100001111 A
b1011010010110100101101001011010 +
b1011010010110100101101001011010 0
b1011010010110100101101001011010 8
b1011010010110100101101001011010 B
#415
1*
#420
b1010000010100000101000001010 !
b1010000010100000101000001010 )
b1010000010100000101000001010 6
0*
b110 .
b110 3
#425
1*
#430
b1010101010101010101010101010101 !
b1010101010101010101010101010101 )
b1010101010101010101010101010101 6
0*
b111 .
b111 3
